faketool-0.1.4.dist-info/DESCRIPTION.rst
faketool-0.1.4.dist-info/METADATA
faketool-0.1.4.dist-info/RECORD
faketool-0.1.4.dist-info/WHEEL
faketool-0.1.4.dist-info/entry_points.txt
faketool-0.1.4.dist-info/metadata.json
faketool-0.1.4.dist-info/top_level.txt
genbank_validate/__init__.py
genbank_validate/breseq_wrapper.py
genbank_validate/cli.py
