Metadata-Version: 2.0
Name: faketool
Version: 0.1.4
Summary: validate and maniopulate genbank files.
Home-page: https://github.com/sgordon007/fake-tool
Author: Sean Gordon
Author-email: seangordon07@gmail.com
License: BSD
Platform: any
Classifier: Development Status :: 4 - Beta
Classifier: Environment :: Console
Classifier: Intended Audience :: Developers
Classifier: License :: OSI Approved :: BSD License
Classifier: Operating System :: POSIX
Classifier: Operating System :: MacOS
Classifier: Operating System :: Unix
Classifier: Operating System :: Microsoft :: Windows
Classifier: Programming Language :: Python
Classifier: Programming Language :: Python :: 2
Classifier: Programming Language :: Python :: 3
Classifier: Topic :: Software Development :: Libraries :: Python Modules
Requires-Dist: biopython
Requires-Dist: click
